{
	"timeline":
	{
		"headline":"设备123 的借入借出记录",
		"type":"default",
		"text":"<p>Intro body text goes here, some HTML is ok</p>",
		"date": [
			{
				"startDate":"2011,12,10",
				"endDate":"2012,12,11",
				"headline":"设备履历开始",
				"text":"<p>Body text goes here, some HTML is OK</p>",
				"tag":"This is Optional"
			}
		],
		"era": [
			{
				"startDate":"2011,12,10",
				"endDate":"2011,12,11",
				"headline":"test1",
				"tag":"This is Optional"
			}
			
		],
		"chart": [
			{
				"startDate":"2012,2,10",
				"endDate":"2012,2,11",
				"headline":"test2",
				"value":"28"
			}
			
		]
		
	}
}
